gicp/__init__.py
gicp/app/__init__.py
gicp/main.py
gicp-0.0.2.dist-info/LICENSE
gicp-0.0.2.dist-info/METADATA
gicp-0.0.2.dist-info/WHEEL
gicp-0.0.2.dist-info/entry_points.txt
gicp-0.0.2.dist-info/RECORD
