Metadata-Version: 2.1
Name: gicp
Version: 0.0.2
Summary: 
Author: Atticuszz
Author-email: 1831768457@qq.com
Requires-Python: >=3.10
Classifier: Programming Language :: Python :: 3
Classifier: Programming Language :: Python :: 3.10
Classifier: Programming Language :: Python :: 3.11
Classifier: Programming Language :: Python :: 3.12
Requires-Dist: small-gicp (>=0.0.3,<0.0.4)
